[{"path":"/home/qiu/listtest/project1/data2/child/LOG","files":[{"filename":"7.log","collected_time":"2023-12-26T09:19:22.543863192Z"},{"filename":"8.log","collected_time":"2023-12-26T09:19:22.544818896Z"},{"filename":"1.log","collected_time":"2023-12-26T09:19:07.544463676Z"},{"filename":"2.log","collected_time":"2023-12-26T09:19:07.544963317Z"},{"filename":"3.log","collected_time":"2023-12-26T09:19:07.545176659Z"},{"filename":"4.log","collected_time":"2023-12-26T09:19:07.545519473Z"},{"filename":"5.log","collected_time":"2023-12-26T09:19:07.546001776Z"},{"filename":"6.log","collected_time":"2023-12-26T09:19:07.546233876Z"}]}]
